hashget/__init__.py
hashget/anchor.py
hashget/cacheget.py
hashget/counters.py
hashget/debian.py
hashget/exceptions.py
hashget/file.py
hashget/filepool.py
hashget/globlist.py
hashget/hashdb.py
hashget/hashpackage.py
hashget/hashutils.py
hashget/heuristic_base.py
hashget/operations.py
hashget/package.py
hashget/restorefile.py
hashget/singlelist.py
hashget/submiturl.py
hashget/utils.py
hashget/version.py
hashget/heuristics/debian/__init__.py
hashget/heuristics/hint/__init__.py
hashget-0.176.data/scripts/hashget
hashget-0.176.data/scripts/hashget-admin
hashget-0.176.dist-info/LICENSE
hashget-0.176.dist-info/METADATA
hashget-0.176.dist-info/WHEEL
hashget-0.176.dist-info/top_level.txt
hashget-0.176.dist-info/RECORD
