Metadata-Version: 2.1
Name: hashget
Version: 0.176
Summary: deduplication tool for archiving data with extremely high ratio
Home-page: https://github.com/yaroslaff/hashget
Author: Yaroslav Polyakov
Author-email: yaroslaff@gmail.com
License: MIT
Platform: UNKNOWN
Classifier: Development Status :: 3 - Alpha
Classifier: Intended Audience :: Developers
Classifier: License :: OSI Approved :: MIT License
Classifier: Programming Language :: Python :: 3.4
Requires-Python: >=3
Requires-Dist: filelock
Requires-Dist: filetype
Requires-Dist: patool
Requires-Dist: requests
Requires-Dist: setuptools
Provides-Extra: plugins
Requires-Dist: hashget-kernel-org ; extra == 'plugins'
